snapshot_ensemble/__init__.py
snapshot_ensemble/snapshot_ensemble.py
snapshot_ensemble/utils.py
snapshot_ensemble-1.0.0.dist-info/LICENSE
snapshot_ensemble-1.0.0.dist-info/METADATA
snapshot_ensemble-1.0.0.dist-info/WHEEL
snapshot_ensemble-1.0.0.dist-info/top_level.txt
snapshot_ensemble-1.0.0.dist-info/RECORD
