Metadata-Version: 2.1
Name: snapshot-ensemble
Version: 1.0.0
Summary: Train TensorFlow Keras models with Cosine Annealing and save an ensemble of models with no additional computational expense.
Home-page: https://github.com/adamvvu/snapshot_ensemble
Author: Adam Wu
Author-email: adamwu1@outlook.com
License: UNKNOWN
Platform: UNKNOWN
Classifier: Intended Audience :: Science/Research
Classifier: Topic :: Scientific/Engineering :: Artificial Intelligence
Classifier: Topic :: Scientific/Engineering :: Information Analysis
Classifier: Programming Language :: Python
Classifier: Operating System :: OS Independent
Classifier: License :: OSI Approved :: MIT License
Requires-Python: >=3.6
License-File: LICENSE
Requires-Dist: numpy
Requires-Dist: tensorflow
Requires-Dist: matplotlib
